codespector/__init__.py
codespector/base.py
codespector/codespector.py
codespector/errors.py
codespector/local.py
codespector/main.py
codespector/reviewer.py
codespector/types.py
codespector-1.0.1.dist-info/METADATA
codespector-1.0.1.dist-info/WHEEL
codespector-1.0.1.dist-info/entry_points.txt
codespector-1.0.1.dist-info/licenses/LICENSE
codespector-1.0.1.dist-info/RECORD
