Metadata-Version: 2.4
Name: codespector
Version: 1.0.1
Summary: Assistant for reviewing your code
Project-URL: Repository, https://github.com/Vladimir-Titov/codespector
Project-URL: Issues, https://github.com/Vladimir-Titov/codespector/issues
Author-email: vtitov <v.v.titov94@gmail.com>
License-File: LICENSE
Classifier: Development Status :: 5 - Production/Stable
Classifier: Programming Language :: Python :: 3.10
Classifier: Programming Language :: Python :: 3.11
Classifier: Programming Language :: Python :: 3.12
Requires-Python: >=3.10
Requires-Dist: click>=8.1.8
Requires-Dist: environs>=14.1.1
Requires-Dist: loguru>=0.7.3
Requires-Dist: requests>=2.32.3
